{"strategies": [{"name": "whale_exit@1.0", "desc": "esci quando escono TUTTE le balene", "kind": "balene", "final": 133.83, "n": 12, "win": 67, "best": ["Bid on The OG ", 136.8]}, {"name": "whale_exit@0.5", "desc": "esci quando ne esce meta'", "kind": "balene", "final": 127.49, "n": 12, "win": 58, "best": ["Bid on The OG ", 136.8]}, {"name": "whale_ladder", "desc": "uscita di prezzo (scale-out+trailing)", "kind": "prezzo", "final": 119.79, "n": 12, "win": 58, "best": ["Bid on The OG ", 121.6]}, {"name": "house_money_3x", "desc": "uscita di prezzo (recupero+trailing)", "kind": "prezzo", "final": 127.57, "n": 12, "win": 50, "best": ["The ONLY and m", 130.9]}], "n_token": 12, "note": "STUDIO in-sample su 12 token smart>=2 storici, NON il conto vivo. Dominato da pochi 'mostri' (coda lunga): direzione, non prova di profittabilita'.", "verdict": "L'uscita sulle BALENE batte l'uscita di PREZZO catturando i mostri (coda lunga)."}